winui3/Microsoft.WindowsAppRuntime.Bootstrap.dll
winui3/_winui3_microsoft_windows_applicationmodel_dynamicdependency_bootstrap.cp311-win_arm64.pyd
winui3/_winui3_microsoft_windows_applicationmodel_dynamicdependency_bootstrap.pyi
winui3/microsoft/windows/applicationmodel/dynamicdependency/bootstrap/__init__.py
winui3/microsoft/windows/applicationmodel/dynamicdependency/bootstrap/py.typed
winui3_microsoft_windows_applicationmodel_dynamicdependency_bootstrap-3.2.1.dist-info/METADATA
winui3_microsoft_windows_applicationmodel_dynamicdependency_bootstrap-3.2.1.dist-info/WHEEL
winui3_microsoft_windows_applicationmodel_dynamicdependency_bootstrap-3.2.1.dist-info/top_level.txt
winui3_microsoft_windows_applicationmodel_dynamicdependency_bootstrap-3.2.1.dist-info/RECORD
